dyne/__init__.py
dyne/__main__.py
dyne/__version__.py
dyne/api.py
dyne/background.py
dyne/cli.py
dyne/core.py
dyne/exceptions.py
dyne/formats.py
dyne/models.py
dyne/routes.py
dyne/staticfiles.py
dyne/statics.py
dyne/status.py
dyne/templates.py
dyne/ext/__init__.py
dyne/ext/auth/__init__.py
dyne/ext/graphql/__init__.py
dyne/ext/graphql/templates.py
dyne/ext/schema/__init__.py
dyne/ext/schema/docs/elements.html
dyne/ext/schema/docs/rapidoc.html
dyne/ext/schema/docs/redoc.html
dyne/ext/schema/docs/swaggerui.html
dyne/fields/__init__.py
dyne/fields/mashmellow/__init__.py
dyne/fields/pydantic/__init__.py
dyne-1.0.10.dist-info/METADATA
dyne-1.0.10.dist-info/WHEEL
dyne-1.0.10.dist-info/licenses/LICENSE
dyne-1.0.10.dist-info/RECORD
