Metadata-Version: 2.4
Name: dyne
Version: 1.0.10
Summary: A light weight Python async framework with batteries included.
Author-email: Tabot Kevin <tabot.kevin@gmail.com>
License-File: LICENSE
Classifier: Environment :: Web Environment
Classifier: Intended Audience :: Developers
Classifier: License :: OSI Approved :: Apache Software License
Classifier: Programming Language :: Python :: 3
Requires-Python: >=3.10
Requires-Dist: a2wsgi>=1.10.7
Requires-Dist: aiofiles>=23.2.1
Requires-Dist: apispec>=1.0.0b1
Requires-Dist: chardet>=5.2.0
Requires-Dist: docopt>=0.6.2
Requires-Dist: flask>=3.0.3
Requires-Dist: graphene>=3.3
Requires-Dist: graphql-server>=3.0.0b7
Requires-Dist: itsdangerous>=2.1.2
Requires-Dist: jinja2>=3.1.3
Requires-Dist: marshmallow>=3.21.1
Requires-Dist: pydantic>=2.7.0
Requires-Dist: python-multipart>=0.0.9
Requires-Dist: pyyaml>=6.0.1
Requires-Dist: requests-toolbelt>=1.0.0
Requires-Dist: requests>=2.31.0
Requires-Dist: rfc3986>=2.0.0
Requires-Dist: sqlalchemy>=2.0.29
Requires-Dist: starlette>=0.37.2
Requires-Dist: uvicorn[standard]>=0.29.0
Requires-Dist: whitenoise>=6.6.0
